setup.py
hailstorm/__init__.py
hailstorm/escape.py
hailstorm/template.py
hailstorm/util.py
hailstorm.egg-info/PKG-INFO
hailstorm.egg-info/SOURCES.txt
hailstorm.egg-info/dependency_links.txt
hailstorm.egg-info/top_level.txt